{
    "program_id": "e05d70b5bfec46528f63447639aafb77",
    "source": {
        "program_id": "e05d70b5bfec46528f63447639aafb77",
        "selected_gate_set": [
            "CRXGate",
            "iSwapGate",
            "CSXGate",
            "CRZGate",
            "SXdgGate",
            "CCXGate",
            "SdgGate",
            "SXGate",
            "UGate",
            "U2Gate",
            "CHGate",
            "RZGate",
            "RCCXGate",
            "RZZGate",
            "ZGate",
            "ECRGate",
            "XGate",
            "CUGate",
            "RYYGate",
            "TGate",
            "CU1Gate",
            "SGate",
            "C3SXGate"
        ],
        "selected_optimization": [],
        "shots": 979,
        "n_qubits": 5,
        "n_ops": 28,
        "opt_level": 2,
        "target_gates": null,
        "py_file_path": "data/qmt_v53/programs/source/e05d70b5bfec46528f63447639aafb77.py",
        "time_generation": 0.005373345920816064,
        "circuit_id": "qc",
        "id_quantum_reg": "qr",
        "id_classical_reg": "cr",
        "gate_set": [
            {
                "name": "CRXGate",
                "n_bits": 2,
                "n_params": 1,
                "shortname": "crx"
            },
            {
                "name": "iSwapGate",
                "n_bits": 2,
                "n_params": 0,
                "shortname": "iswap"
            },
            {
                "name": "CSXGate",
                "n_bits": 2,
                "n_params": 0,
                "shortname": "csx"
            },
            {
                "name": "CRZGate",
                "n_bits": 2,
                "n_params": 1,
                "shortname": "crz"
            },
            {
                "name": "SXdgGate",
                "n_bits": 1,
                "n_params": 0,
                "shortname": "sxdg"
            },
            {
                "name": "CCXGate",
                "n_bits": 3,
                "n_params": 0,
                "shortname": "ccx"
            },
            {
                "name": "SdgGate",
                "n_bits": 1,
                "n_params": 0,
                "shortname": "sdg"
            },
            {
                "name": "SXGate",
                "n_bits": 1,
                "n_params": 0,
                "shortname": "sx"
            },
            {
                "name": "UGate",
                "n_bits": 1,
                "n_params": 3,
                "shortname": "u"
            },
            {
                "name": "U2Gate",
                "n_bits": 1,
                "n_params": 2,
                "shortname": "u2"
            },
            {
                "name": "CHGate",
                "n_bits": 2,
                "n_params": 0,
                "shortname": "ch"
            },
            {
                "name": "RZGate",
                "n_bits": 1,
                "n_params": 1,
                "shortname": "rz"
            },
            {
                "name": "RCCXGate",
                "n_bits": 3,
                "n_params": 0,
                "shortname": "rccx"
            },
            {
                "name": "RZZGate",
                "n_bits": 2,
                "n_params": 1,
                "shortname": "rzz"
            },
            {
                "name": "ZGate",
                "n_bits": 1,
                "n_params": 0,
                "shortname": "z"
            },
            {
                "name": "ECRGate",
                "n_bits": 2,
                "n_params": 0,
                "shortname": "ecr"
            },
            {
                "name": "XGate",
                "n_bits": 1,
                "n_params": 0,
                "shortname": "x"
            },
            {
                "name": "CUGate",
                "n_bits": 2,
                "n_params": 4,
                "shortname": "cu"
            },
            {
                "name": "RYYGate",
                "n_bits": 2,
                "n_params": 1,
                "shortname": "ryy"
            },
            {
                "name": "TGate",
                "n_bits": 1,
                "n_params": 0,
                "shortname": "t"
            },
            {
                "name": "CU1Gate",
                "n_bits": 2,
                "n_params": 1,
                "shortname": "cu1"
            },
            {
                "name": "SGate",
                "n_bits": 1,
                "n_params": 0,
                "shortname": "s"
            },
            {
                "name": "C3SXGate",
                "n_bits": 4,
                "n_params": 0
            }
        ],
        "gates_in_circuit": [
            "CU1Gate",
            "CRZGate",
            "RYYGate",
            "XGate",
            "CSXGate",
            "TGate",
            "SXdgGate",
            "CRXGate",
            "ECRGate",
            "SGate",
            "ZGate",
            "RZGate",
            "CUGate",
            "RCCXGate",
            "CHGate",
            "UGate"
        ]
    },
    "followup": {
        "program_id": "e05d70b5bfec46528f63447639aafb77",
        "selected_gate_set": [
            "CRXGate",
            "iSwapGate",
            "CSXGate",
            "CRZGate",
            "SXdgGate",
            "CCXGate",
            "SdgGate",
            "SXGate",
            "UGate",
            "U2Gate",
            "CHGate",
            "RZGate",
            "RCCXGate",
            "RZZGate",
            "ZGate",
            "ECRGate",
            "XGate",
            "CUGate",
            "RYYGate",
            "TGate",
            "CU1Gate",
            "SGate",
            "C3SXGate"
        ],
        "selected_optimization": [],
        "shots": 979,
        "n_qubits": 5,
        "n_ops": 28,
        "opt_level": 2,
        "target_gates": null,
        "py_file_path": "data/qmt_v53/programs/followup/e05d70b5bfec46528f63447639aafb77.py",
        "time_generation": 0.005373345920816064,
        "circuit_id": "qc",
        "id_quantum_reg": "qr",
        "id_classical_reg": "cr",
        "gate_set": [
            {
                "name": "CRXGate",
                "n_bits": 2,
                "n_params": 1,
                "shortname": "crx"
            },
            {
                "name": "iSwapGate",
                "n_bits": 2,
                "n_params": 0,
                "shortname": "iswap"
            },
            {
                "name": "CSXGate",
                "n_bits": 2,
                "n_params": 0,
                "shortname": "csx"
            },
            {
                "name": "CRZGate",
                "n_bits": 2,
                "n_params": 1,
                "shortname": "crz"
            },
            {
                "name": "SXdgGate",
                "n_bits": 1,
                "n_params": 0,
                "shortname": "sxdg"
            },
            {
                "name": "CCXGate",
                "n_bits": 3,
                "n_params": 0,
                "shortname": "ccx"
            },
            {
                "name": "SdgGate",
                "n_bits": 1,
                "n_params": 0,
                "shortname": "sdg"
            },
            {
                "name": "SXGate",
                "n_bits": 1,
                "n_params": 0,
                "shortname": "sx"
            },
            {
                "name": "UGate",
                "n_bits": 1,
                "n_params": 3,
                "shortname": "u"
            },
            {
                "name": "U2Gate",
                "n_bits": 1,
                "n_params": 2,
                "shortname": "u2"
            },
            {
                "name": "CHGate",
                "n_bits": 2,
                "n_params": 0,
                "shortname": "ch"
            },
            {
                "name": "RZGate",
                "n_bits": 1,
                "n_params": 1,
                "shortname": "rz"
            },
            {
                "name": "RCCXGate",
                "n_bits": 3,
                "n_params": 0,
                "shortname": "rccx"
            },
            {
                "name": "RZZGate",
                "n_bits": 2,
                "n_params": 1,
                "shortname": "rzz"
            },
            {
                "name": "ZGate",
                "n_bits": 1,
                "n_params": 0,
                "shortname": "z"
            },
            {
                "name": "ECRGate",
                "n_bits": 2,
                "n_params": 0,
                "shortname": "ecr"
            },
            {
                "name": "XGate",
                "n_bits": 1,
                "n_params": 0,
                "shortname": "x"
            },
            {
                "name": "CUGate",
                "n_bits": 2,
                "n_params": 4,
                "shortname": "cu"
            },
            {
                "name": "RYYGate",
                "n_bits": 2,
                "n_params": 1,
                "shortname": "ryy"
            },
            {
                "name": "TGate",
                "n_bits": 1,
                "n_params": 0,
                "shortname": "t"
            },
            {
                "name": "CU1Gate",
                "n_bits": 2,
                "n_params": 1,
                "shortname": "cu1"
            },
            {
                "name": "SGate",
                "n_bits": 1,
                "n_params": 0,
                "shortname": "s"
            },
            {
                "name": "C3SXGate",
                "n_bits": 4,
                "n_params": 0
            }
        ],
        "gates_in_circuit": [
            "CU1Gate",
            "CRZGate",
            "RYYGate",
            "XGate",
            "CSXGate",
            "TGate",
            "SXdgGate",
            "CRXGate",
            "ECRGate",
            "SGate",
            "ZGate",
            "RZGate",
            "CUGate",
            "RCCXGate",
            "CHGate",
            "UGate"
        ],
        "metamorphic_info": {
            "0": {
                "edge_density": 0.07859895570699452,
                "new_coupling_map": [
                    [
                        0,
                        1
                    ],
                    [
                        1,
                        0
                    ],
                    [
                        1,
                        2
                    ],
                    [
                        1,
                        3
                    ],
                    [
                        1,
                        4
                    ],
                    [
                        2,
                        1
                    ],
                    [
                        3,
                        1
                    ],
                    [
                        4,
                        1
                    ]
                ]
            }
        },
        "metamorphic_transformations": [
            "ChangeCouplingMap"
        ],
        "time_metamorph": 0.020068967947736382,
        "metamorphic_transformations_times": [
            0.01718264096416533
        ]
    },
    "divergence": {
        "ks": {
            "statistic": 0.07763023493360573,
            "p-value": 0.005463478393047937,
            "time": 0.0031395400874316692
        }
    },
    "time_exec": 0.7052132089156657,
    "abs_start_time": 1660075765,
    "exceptions": {
        "source": null,
        "followup": null
    }
}